dist/ut_prc-1.0.0.20250730-py3-none-any.whl
dist/ut_prc-1.0.0.20250730.tar.gz
ut_prc/__init__.py
ut_prc/__version__.py
ut_prc/prc.py
ut_prc/py.typed
ut_prc-1.0.0.20250730.dist-info/licenses/LICENSE.txt
ut_prc-1.0.0.20250730.dist-info/METADATA
ut_prc-1.0.0.20250730.dist-info/WHEEL
ut_prc-1.0.0.20250730.dist-info/top_level.txt
ut_prc-1.0.0.20250730.dist-info/RECORD
