Metadata-Version: 2.4
Name: ut_prc
Version: 1.0.0.20250730
Summary: Process and Thread Management Utilities
Author: Bernd Stroehle
Author-email: bernd.stroehle@gmail.com
Maintainer: Bernd Stroehle
Maintainer-email: bernd.stroehle@gmail.com
License-Expression: GPL-3.0-only WITH Classpath-exception-2.0 OR BSD-3-Clause
Project-URL: Source Code, https://github.com/bs29/ut_prc/tree/master
Project-URL: Homepage, https://kosakya.de/
Project-URL: Documentation, https://ka-apc.readthedocs.io/en/latest
Project-URL: Apache-2.0 License, https://apache.org/licenses/LICENSE-2.0
Project-URL: GPLv3 License, https://www.gnu.org/licenses/gpl-3.0.en.html
Classifier: Development Status :: 5 - Production/Stable
Classifier: Intended Audience :: Developers
Classifier: Operating System :: OS Independent
Classifier: Programming Language :: Python :: 3.11
Classifier: Natural Language :: English
Classifier: Topic :: Software Development :: Libraries :: Python Modules
Requires-Python: >=3.10
License-File: LICENSE.txt
Requires-Dist: joblib>=1.4.2
Requires-Dist: ut_com>=1.0.0.20250715
Requires-Dist: ut_dic>=1.0.0.20250719
Dynamic: license-file
